ccbhc_measurements/__init__.py
ccbhc_measurements/abstractions/__init__.py
ccbhc_measurements/abstractions/denominator.py
ccbhc_measurements/abstractions/measurement.py
ccbhc_measurements/abstractions/numerator.py
ccbhc_measurements/abstractions/stratification.py
ccbhc_measurements/abstractions/submeasure.py
ccbhc_measurements/compat/__init__.py
ccbhc_measurements/compat/typing_compat.py
ccbhc_measurements/demos/__init__.py
ccbhc_measurements/demos/asc_sub_1_demo.py
ccbhc_measurements/demos/cdf_ad_demo.py
ccbhc_measurements/demos/cdf_ch_demo.py
ccbhc_measurements/demos/dep_rem_demo.py
ccbhc_measurements/demos/main_demo.py
ccbhc_measurements/demos/sdoh_demo.py
ccbhc_measurements/measurements/__init__.py
ccbhc_measurements/measurements/asc.py
ccbhc_measurements/measurements/cdf_ad.py
ccbhc_measurements/measurements/cdf_ch.py
ccbhc_measurements/measurements/dep_rem.py
ccbhc_measurements/measurements/sdoh.py
ccbhc_measurements/strategies/__init__.py
ccbhc_measurements/strategies/alcohol_screening_strategies.py
ccbhc_measurements/validation/__init__.py
ccbhc_measurements/validation/required_data.py
ccbhc_measurements/validation/schemas.py
ccbhc_measurements/validation/validation_factory.py
ccbhc_measurements/validation/validator.py
ccbhc_measurements-2025.11.6.dist-info/licenses/LICENSE
ccbhc_measurements-2025.11.6.dist-info/METADATA
ccbhc_measurements-2025.11.6.dist-info/WHEEL
ccbhc_measurements-2025.11.6.dist-info/top_level.txt
ccbhc_measurements-2025.11.6.dist-info/RECORD
