Metadata-Version: 2.4
Name: ccbhc_measurements
Version: 2025.11.6
Summary: An easy way to calculate CCBHC measurements.
Home-page: https://github.com/Pesach-Tikvah-Hope-Development-Inc/CCBHC_Measurements
Author: Pesach Tikvah Hope Development Inc.
Author-email: "Pesach Tikvah Hope Development Inc." <agursky@pesachtikvah.org>
Maintainer: Alex Gursky, Max Friedman, Yisroel Len
Maintainer-email: Alex Gursky <agursky@pesachtikvah.org>, Max Friedman <mfriedman@pesachtikvah.org>, Yisroel Len <ylen@pesachtikvah.org>
License: CCBHC Measurements Calculation © 2025 by Alex Gursky and Yisroel Len is licensed under Creative Commons Attribution-NonCommercial-ShareAlike 4.0 International.
Project-URL: Documentaion, https://github.com/Pesach-Tikvah-Hope-Development-Inc/CCBHC_Measurements
Project-URL: Repository, https://github.com/Pesach-Tikvah-Hope-Development-Inc/CCBHC_Measurements
Classifier: License :: Free for non-commercial use
Classifier: Intended Audience :: Healthcare Industry
Classifier: Intended Audience :: Developers
Classifier: Programming Language :: Python :: 3.12
Requires-Python: >=3.12
License-File: LICENSE
Requires-Dist: pandas>=2.2.2
Requires-Dist: python-dateutil>=2.8.2
Requires-Dist: tzdata>=2022.7
Dynamic: author
Dynamic: home-page
Dynamic: license-file
Dynamic: maintainer
Dynamic: requires-python
